LICENSE
MANIFEST.in
README.md
requirements.txt
setup.py
birdy/__init__.py
birdy/twitter.py
birdy.egg-info/PKG-INFO
birdy.egg-info/SOURCES.txt
birdy.egg-info/dependency_links.txt
birdy.egg-info/not-zip-safe
birdy.egg-info/requires.txt
birdy.egg-info/top_level.txt