Metadata-Version: 1.1
Name: birdy
Version: 0.3.2
Summary: birdy is a super awesome Twitter API client for Python.
Home-page: https://github.com/inueni/birdy/
Author: Mitja Pagon
Author-email: mitja@inueni.com
License: MIT
Keywords: t,w,i,t,t,e,r, ,a,p,i, ,t,w,e,e,t, ,b,i,r,d,y, ,s,e,a,r,c,h
Platform: UNKNOWN
Classifier: Development Status :: 5 - Production/Stable
Classifier: Environment :: Web Environment
Classifier: Intended Audience :: Developers
Classifier: Operating System :: OS Independent
Classifier: License :: OSI Approved :: MIT License
Classifier: Topic :: Software Development :: Libraries :: Python Modules
Classifier: Topic :: Communications :: Chat
Classifier: Topic :: Internet
Classifier: Programming Language :: Python
Classifier: Programming Language :: Python :: 2
Classifier: Programming Language :: Python :: 2.7
Classifier: Programming Language :: Python :: 3
Classifier: Programming Language :: Python :: 3.4
Classifier: Programming Language :: Python :: 3.5
Classifier: Programming Language :: Python :: 3.6
